[
	"Uma picareta ativada por um dispensor simples pode quebrar blocos autamaticamente.",
	"Se esta máquina é colocada em frente de um bloco destruível e ativada por um pulso de redstone, ela quebra o bloco e o solta atrás.",
	
	"Criando:",
	{
		"type": "crafting",
		"slots":
		{
			"1": {"OreDict":"ingotAluminum"},
			"2": {"OreDict":"ingotAluminum"},
			"3": {"OreDict":"ingotAluminum"},
			"4": {"OreDict":"ingotAluminum"},
			"5": {"name":"minecraft:dispenser","meta":0},
			"6": {"OreDict":"ingotAluminum"},
			"7": {"name":"minecraft:obsidian","meta":0},
			"8": {"name":"minecraft:iron_pickaxe","meta":0},
			"9": {"name":"minecraft:obsidian","meta":0},
			"out": {"name":"futurepack:block_breaker","meta":0}
		}
	},
	
	"A máquina pode ser melhorado colocando livros encantados dentro."
]
